guertena/__init__.py
guertena/driver.py
guertena/styletransfernet.py
guertena-0.0.5.dist-info/LICENSE
guertena-0.0.5.dist-info/METADATA
guertena-0.0.5.dist-info/WHEEL
guertena-0.0.5.dist-info/top_level.txt
guertena-0.0.5.dist-info/RECORD
