Metadata-Version: 2.1
Name: guertena
Version: 0.0.5
Summary: Guertena is an easy to use, quality oriented python library for neural style transfer.
Home-page: https://github.com/albarji/guertena
Author: Alvaro Barbero
License: MIT
Keywords: artificial-intelligence,deep-learning,neural-style-transfer
Platform: UNKNOWN
Classifier: Development Status :: 1 - Planning
Classifier: Environment :: GPU :: NVIDIA CUDA
Classifier: Intended Audience :: Science/Research
Classifier: License :: OSI Approved :: MIT License
Classifier: Operating System :: Unix
Classifier: Programming Language :: Python :: 3.7
Classifier: Programming Language :: Python :: 3.8
Classifier: Programming Language :: Python :: 3.9
Classifier: Topic :: Artistic Software
Classifier: Topic :: Multimedia :: Graphics
License-File: LICENSE
Requires-Dist: numpy (<2,>=1.19)
Requires-Dist: torch (<2,>=1.9)
Requires-Dist: torchvision (<1,>=0.10)
